LICENSE
MANIFEST.in
README.md
setup.py
pedsnetcdms/__init__.py
pedsnetcdms/dj_makers.py
pedsnetcdms/manage.py
pedsnetcdms/sa_makers.py
pedsnetcdms/settings.py
pedsnetcdms.egg-info/PKG-INFO
pedsnetcdms.egg-info/SOURCES.txt
pedsnetcdms.egg-info/dependency_links.txt
pedsnetcdms.egg-info/requires.txt
pedsnetcdms.egg-info/top_level.txt
pedsnetcdms/itwobtwocdm/__init__.py
pedsnetcdms/itwobtwocdm/models.json
pedsnetcdms/itwobtwocdm/models.py
pedsnetcdms/itwobtwocdm/sa_models.py
pedsnetcdms/itwobtwocdm/migrations/0001_initial.py
pedsnetcdms/itwobtwocdm/migrations/__init__.py
pedsnetcdms/pcornetcdm/__init__.py
pedsnetcdms/pcornetcdm/models.json
pedsnetcdms/pcornetcdm/models.py
pedsnetcdms/pcornetcdm/sa_models.py
pedsnetcdms/pcornetcdm/migrations/0001_initial.py
pedsnetcdms/pcornetcdm/migrations/__init__.py
pedsnetcdms/pedsnetcdm/__init__.py
pedsnetcdms/pedsnetcdm/models.json
pedsnetcdms/pedsnetcdm/models.py
pedsnetcdms/pedsnetcdm/sa_models.py
pedsnetcdms/pedsnetcdm/migrations/0001_initial.py
pedsnetcdms/pedsnetcdm/migrations/__init__.py
pedsnetcdms/vocabcdm/__init__.py
pedsnetcdms/vocabcdm/models.json
pedsnetcdms/vocabcdm/models.py
pedsnetcdms/vocabcdm/sa_models.py
pedsnetcdms/vocabcdm/migrations/0001_initial.py
pedsnetcdms/vocabcdm/migrations/__init__.py