Metadata-Version: 1.1
Name: pedsnetcdms
Version: 0.1
Summary: PEDSnet Common Data Model Definitions
Home-page: https://github.com/PEDSnet/Data_Models
Author: The Children's Hospital of Philadelphia
Author-email: cbmisupport@email.chop.edu
License: UNKNOWN
Download-URL: https://github.com/PEDSnet/pedsnetcdms/tarball/0.1
Platform: UNKNOWN
